{
  "zESL": [
    {
      "id": "C4D8D52CF106",
      "device_id": "UU3QH2025-00001",
      "device_name": "C4D8D52CF106",
      "device_category": "esl_ESP8266",
      "device_size": "2.13 inch",
      "device_type": "esl",
      "device_board": "ESP8266",
      "device_chip": "2945286",
      "device_identity": "2945",
      "device_location": "device_location",
      "device_connected": true,
      "device_screen": true,
      "device_key": "2V5Q7Y9MP7",
      "device_version": "1.0.0",
      "base_mac_address": "C4:D8:D5:2C:F1:06",
      "base_ip_address": "172.30.227.148",
      "base_server": "http://172.30.227.230:8080",
      "base_endpoint": "/device",
      "base_wifi_ssid": "SUNDUNG",
      "base_wifi_password": "zx160622",
      "base_server_connected": "",
      "client_ip_address": "172.30.227.148",
      "client_server": "",
      "client_endpoint": "",
      "client_wifi_ssid": "",
      "client_wifi_password": "",
      "client_owner_id": "",
      "client_store_id": "",
      "client_location": "",
      "client_server_connected": true,
      "deleted": false,
      "status": 0,
      "updated": false,
      "live_date": "2025-07-20 17:29:15",
      "live_end": "2025-07-20 17:29:15",
      "created_date": "2025-07-20 17:29:15",
      "last_updated": "2025-07-24 13:42:19",
      "created_by": "hardware",
      "template": 1,
      "content_header1": "Header 1 (17)",
      "content_header2": "Header 2 (17)",
      "content_header_right": "code(13)",
      "content_footer_center": "50000",
      "content_footer_left": "10%",
      "content_footer_strike": "70000",
      "content_footer_right": "100gr",
      "content_footer_center_sub": "2024-10-20",
      "content_footer_right_sub": "Stock: 12",
      "device_token": "eyJhbGciOiJIUzI1NiIsInR5cCI6IkpXVCJ9.eyJpZCI6IkM0RDhENTJDRjEwNiIsInJvbGUiOiJkZXZpY2VfRVNMIiwiZXhwIjoxNzU0ODA3MzU1LCJleHBEYXRlIjoiMjAyNS0xMC0xOCAxNzoyOToxNS4wNjk3ODgifQ.dAJQn4ZvYRO--2jiXly6GSbPZExsR9Zzl2n86A8dJV4",
      "code": 200,
      "message": "Data Updated"
    }
  ]
}