[
  {
    "location": {
      "zone": 1,
      "aisle": 0,
      "section": 0,
      "position": 0,
      "level": 0,
      "rack": 0,
      "color": "Black"
    },
    "size": {
      "weight": 300,
      "height": 300,
      "width": 100,
      "dimension": 0,
      "color": "Black",
      "uom": "ml"
    },
    "store": [
      {
        "store_id": "outlet563c7d638bba.202506-3017-2343.dfad1",
        "company_id": "202506.3015.3124.a00ed0f9-8e9f-48f0-a322-563c7d638bba"
      },
      {
        "store_id": "outlet563c7d638bba.202507-0111-5901.e3f80",
        "company_id": "202506.3015.3124.a00ed0f9-8e9f-48f0-a322-563c7d638bba"
      }
    ],
    "sku": "3218378172",
    "item_name": "The Botol 300 ml",
    "item_category": "Minuman",
    "item_price": "9500",
    "item_desc": "Teh Botol Original",
    "item_active": true,
    "item_disc": "0",
    "item_price_disc": "0",
    "item_disc_status": false,
    "item_image": "",
    "item_qris": "https://www.google.com",
    "item_qris_status": false,
    "activate": true,
    "deleted": false
  }
]